setup.cfg
setup.py
named_dates/__init__.py
named_dates/named_dates.py
named_dates/work.py
named_dates.egg-info/PKG-INFO
named_dates.egg-info/SOURCES.txt
named_dates.egg-info/dependency_links.txt
named_dates.egg-info/top_level.txt