Metadata-Version: 1.1
Name: named-dates
Version: 0.1
Summary: Date logic for those referred to by name
Home-page: https://github.com/pschoenfelder/named-dates
Author: Paul Schoenfelder
Author-email: schoenfelder.p@gmail.com
License: MIT
Download-URL: https://github.com/pschoenfelder/named-dates/tarball/0.1
Platform: UNKNOWN
Requires: pytest
